CHANGELOG.md
LICENSE
README.md
examples/README.md
gpiodevice/__init__.py
gpiodevice/errors.py
gpiodevice/platform/__init__.py
gpiodevice/platform/alienware.py
gpiodevice/platform/pi.py
gpiodevice/platform/radxa.py
gpiodevice-0.0.4.dist-info/METADATA
gpiodevice-0.0.4.dist-info/WHEEL
gpiodevice-0.0.4.dist-info/licenses/LICENSE
gpiodevice-0.0.4.dist-info/RECORD
